zouqi/__init__.py
zouqi/core.py
zouqi/parsing.py
zouqi/typing.py
zouqi/utils.py
zouqi-1.0.9.dist-info/LICENSE
zouqi-1.0.9.dist-info/METADATA
zouqi-1.0.9.dist-info/WHEEL
zouqi-1.0.9.dist-info/top_level.txt
zouqi-1.0.9.dist-info/RECORD
