Metadata-Version: 2.1
Name: zouqi
Version: 1.0.9
Summary: zouqi is a CLI starter similar to python-fire. It is purely built on argparse.
Home-page: https://github.com/enhuiz/zouqi
Author: enhuiz
Author-email: niuzhe.nz@outlook.com
License: UNKNOWN
Platform: UNKNOWN
Requires-Python: >=3.6.0
Requires-Dist: pyyaml
